{
  "index": 0,
  "id": "2062629868395708435",
  "url": "https://x.com/wufantouzi/status/2062629868395708435",
  "author": {
    "name": "wu fan",
    "handle": "wufantouzi",
    "profileUrl": "https://x.com/wufantouzi"
  },
  "text": "Ai 干掉脑力劳动者\n机器人干掉体力劳动者\n等宇树科技 IPO\n该冲还是要冲的\n\n趋势已经很明显了\n…\nSubscribe to unlock",
  "translated": false,
  "createdAt": "2026-06-04T20:17:37.000Z",
  "visibleTime": "4:17 AM · Jun 5, 2026",
  "metrics": {
    "views": "46"
  },
  "images": [],
  "links": [],
  "schemaVersion": 3,
  "source": "x",
  "capturedAt": "2026-07-04T15:56:45.828Z",
  "capturedFromUrl": "https://x.com/wufantouzi/status/2062629868395708435",
  "blockedCommentCount": 0,
  "comments": []
}
