{
  "index": 0,
  "id": "2062218300482900366",
  "url": "https://x.com/wufantouzi/status/2062218300482900366",
  "author": {
    "name": "wu fan",
    "handle": "wufantouzi",
    "profileUrl": "https://x.com/wufantouzi"
  },
  "text": "皮克斯阶段\n是乔布斯的人生低谷\n但那是苹果的大招CD时间\n没有这段经历就不会有乔帮主\n\n不要浪费每一次危机\n市场的危机是抄底的好时机\n人生的危机是脱茧化蝶的过程\n当下的痛苦是起飞前的历练\n经历过才是真正的跨越\nQuote\n美少女战士_Ayla\n@Aylababe_\nReplit founder Amjad Masad said that the toughest story about Jobs isn't Apple, but the 12 years after he was ousted from Apple.\n\nHe shelled out $5 million to buy Pixar, then poured in another $50 million over time, losing money for 10 years straight, personally writing checks to\n2:32\n1:02 AM · Jun 4, 2026",
  "translated": false,
  "createdAt": "2026-06-03T03:11:20.000Z",
  "visibleTime": "Jun 3",
  "metrics": {
    "replies": "5",
    "reposts": "3",
    "likes": "29",
    "bookmarks": "15",
    "views": "15946"
  },
  "images": [],
  "links": [],
  "schemaVersion": 3,
  "source": "x",
  "capturedAt": "2026-07-04T16:00:05.644Z",
  "capturedFromUrl": "https://x.com/wufantouzi/status/2062218300482900366",
  "blockedCommentCount": 0,
  "comments": [
    {
      "index": 1,
      "id": "2062223475398611356",
      "url": "https://x.com/ablenavy/status/2062223475398611356",
      "author": {
        "name": "iGarlic",
        "handle": "ablenavy",
        "profileUrl": "https://x.com/ablenavy"
      },
      "text": "原来低谷是在读条放大招啊！那我现在的痛苦是不是意味着我要变超级赛亚人了？",
      "translated": false,
      "createdAt": "2026-06-03T17:22:45.000Z",
      "visibleTime": "Jun 4",
      "metrics": {
        "views": "133"
      },
      "images": [],
      "links": [],
      "relation": "visible-reply"
    },
    {
      "index": 2,
      "id": "2062220064795861141",
      "url": "https://x.com/tothemoonjustin/status/2062220064795861141",
      "author": {
        "name": "全职交易员",
        "handle": "tothemoonjustin",
        "profileUrl": "https://x.com/tothemoonjustin"
      },
      "text": "市场现在的危机还没到来，crcl已经快又要腰斩，纳斯达克历史高位，你猜它回调30%，crcl会去哪里？它会跌90%",
      "translated": false,
      "createdAt": "2026-06-03T17:09:12.000Z",
      "visibleTime": "Jun 4",
      "metrics": {
        "views": "171"
      },
      "images": [],
      "links": [],
      "relation": "visible-reply"
    },
    {
      "index": 3,
      "id": "2062218543807283466",
      "url": "https://x.com/g_tsydwqlc/status/2062218543807283466",
      "author": {
        "name": "Gate-85.Helen直开",
        "handle": "g_tsydwqlc",
        "profileUrl": "https://x.com/g_tsydwqlc"
      },
      "text": "crises make you stronger man",
      "translated": false,
      "createdAt": "2026-06-03T17:03:09.000Z",
      "visibleTime": "Jun 4",
      "metrics": {
        "views": "150"
      },
      "images": [],
      "links": [],
      "relation": "visible-reply"
    }
  ]
}
