{
  "index": 0,
  "id": "2067675500747612385",
  "url": "https://x.com/wufantouzi/status/2067675500747612385",
  "author": {
    "name": "wu fan",
    "handle": "wufantouzi",
    "profileUrl": "https://x.com/wufantouzi"
  },
  "text": "Ai的概念太强了\n各种几倍杠杆etf产品\n都干到几百亿美金体量\n从这个角度说\nAi也抢走了短线赌博用户\n\n谁还玩btc玩合约啊\n这些Ai的etf产品\n日波动20-30%还不爆仓\n半年波动十几倍\n\n所以cex是感受最明显的\n赶紧把这些标的都上了合约\n包括世界杯都是被影响的\n反正都是赌\nAi的杠杆etf产品好玩还赚钱\n还赌球个毛啊\n\n这就是过去半年的事情\n至于之后什么表现\n我也不知道\n我只是表达一个现象",
  "translated": false,
  "createdAt": "2026-06-18T18:27:09.000Z",
  "visibleTime": "2:27 AM · Jun 19, 2026",
  "metrics": {
    "replies": "58",
    "repost": "1",
    "likes": "54",
    "bookmarks": "15",
    "views": "21903"
  },
  "images": [],
  "links": [],
  "schemaVersion": 3,
  "source": "x",
  "capturedAt": "2026-07-04T15:51:47.105Z",
  "capturedFromUrl": "https://x.com/wufantouzi/status/2067675500747612385",
  "blockedCommentCount": 0,
  "comments": [
    {
      "index": 1,
      "id": "2067848929375601005",
      "url": "https://x.com/ablenavy/status/2067848929375601005",
      "author": {
        "name": "iGarlic",
        "handle": "ablenavy",
        "profileUrl": "https://x.com/ablenavy"
      },
      "text": "没错，这几倍杠杆的AI ETF波动大又不容易爆仓，确实比玩币圈合约更有吸引力。",
      "translated": false,
      "createdAt": "2026-06-19T05:56:18.000Z",
      "visibleTime": "Jun 19",
      "metrics": {
        "views": "106"
      },
      "images": [],
      "links": [],
      "relation": "visible-reply"
    },
    {
      "index": 2,
      "id": "2067991536298795431",
      "url": "https://x.com/sjl166/status/2067991536298795431",
      "author": {
        "name": "斯嘉丽 Scar",
        "handle": "sjl166",
        "profileUrl": "https://x.com/sjl166"
      },
      "text": "寻找刺激感",
      "translated": false,
      "createdAt": "2026-06-19T15:22:58.000Z",
      "visibleTime": "Jun 19",
      "metrics": {
        "views": "187"
      },
      "images": [],
      "links": [],
      "relation": "visible-reply"
    },
    {
      "index": 3,
      "id": "2067677148052431025",
      "url": "https://x.com/WeiJiang194454/status/2067677148052431025",
      "author": {
        "name": "灰度先生",
        "handle": "WeiJiang194454",
        "profileUrl": "https://x.com/WeiJiang194454"
      },
      "text": "最危险的不是会爆仓的合约，而是不爆仓却每天剧烈波动的产品。它给人一种错觉：我不是赌博，我是在投资未来。",
      "translated": false,
      "createdAt": "2026-06-18T18:33:42.000Z",
      "visibleTime": "Jun 19",
      "metrics": {
        "repost": "1",
        "likes": "2",
        "views": "935"
      },
      "images": [],
      "links": [],
      "relation": "visible-reply"
    },
    {
      "index": 4,
      "id": "2067687814435663990",
      "url": "https://x.com/tothemoonjustin/status/2067687814435663990",
      "author": {
        "name": "全职交易员",
        "handle": "tothemoonjustin",
        "profileUrl": "https://x.com/tothemoonjustin"
      },
      "text": "讲真，基金没人维权吗。。。",
      "translated": false,
      "createdAt": "2026-06-18T19:16:05.000Z",
      "visibleTime": "Jun 19",
      "metrics": {
        "likes": "3",
        "views": "1188"
      },
      "images": [],
      "links": [],
      "relation": "visible-reply"
    },
    {
      "index": 5,
      "id": "2067687192189718901",
      "url": "https://x.com/tothemoonjustin/status/2067687192189718901",
      "author": {
        "name": "全职交易员",
        "handle": "tothemoonjustin",
        "profileUrl": "https://x.com/tothemoonjustin"
      },
      "text": "180喊单\n$MSTR\n170喊单\n$CRCL\n哈哈哈\nStrategy Inc\nMSTR\n$100.77\n+7.90%\nCircle Internet Group Inc\nCRCL\n$64.62\n+4.31%",
      "translated": false,
      "createdAt": "2026-06-18T19:13:37.000Z",
      "visibleTime": "Jun 19",
      "metrics": {
        "likes": "3",
        "views": "609"
      },
      "images": [],
      "links": [],
      "relation": "visible-reply"
    }
  ]
}
