{
  "index": 0,
  "id": "2069495557739999354",
  "url": "https://x.com/wufantouzi/status/2069495557739999354",
  "author": {
    "name": "wu fan",
    "handle": "wufantouzi",
    "profileUrl": "https://x.com/wufantouzi"
  },
  "text": "我也有那种一时冲动买进去的标的\n哪怕买的不多\n一跌就想跑\n因为根本不知道底在哪\n它到底值得多少钱\n所以大仓位这些票买不出手",
  "translated": false,
  "createdAt": "2026-06-23T18:59:24.000Z",
  "visibleTime": "2:59 AM · Jun 24, 2026",
  "metrics": {
    "replies": "4",
    "repost": "1",
    "likes": "28",
    "bookmark": "1",
    "views": "13459"
  },
  "images": [],
  "links": [],
  "schemaVersion": 3,
  "source": "x",
  "capturedAt": "2026-07-04T15:45:14.731Z",
  "capturedFromUrl": "https://x.com/wufantouzi/status/2069495557739999354",
  "blockedCommentCount": 0,
  "comments": [
    {
      "index": 1,
      "id": "2073254843226161559",
      "url": "https://x.com/JobberTheGuru/status/2073254843226161559",
      "author": {
        "name": "召北",
        "handle": "JobberTheGuru",
        "profileUrl": "https://x.com/JobberTheGuru"
      },
      "text": "这场闹剧该结束了！",
      "translated": false,
      "createdAt": "2026-07-04T03:57:28.000Z",
      "visibleTime": "11h",
      "metrics": {
        "replies": "38",
        "likes": "30",
        "bookmarks": "5",
        "views": "16522"
      },
      "images": [
        {
          "alt": "Image",
          "url": "https://pbs.twimg.com/media/HMWuSQVa8AAffS6?format=jpg&name=large"
        }
      ],
      "links": [],
      "relation": "visible-reply"
    },
    {
      "index": 2,
      "id": "2073357923389161582",
      "url": "https://x.com/ShannonHar2140/status/2073357923389161582",
      "author": {
        "name": "比特币香山",
        "handle": "ShannonHar2140",
        "profileUrl": "https://x.com/ShannonHar2140"
      },
      "text": "6万是底，回到前高12.6万，仅仅翻一倍。\n\n4万是底，回到前高，翻3倍。\n\n3万是底，回到前高，翻4倍。\n\n6万是底，即使涨到9万，也仅仅涨了50%。\n\n3万是底，涨到9万，已经翻了三倍。",
      "translated": false,
      "createdAt": "2026-07-04T10:47:04.000Z",
      "visibleTime": "4h",
      "metrics": {
        "replies": "12",
        "likes": "19",
        "bookmarks": "2",
        "views": "6702"
      },
      "images": [],
      "links": [],
      "relation": "visible-reply"
    },
    {
      "index": 3,
      "id": "2073235787404259530",
      "url": "https://x.com/xzzzjpl/status/2073235787404259530",
      "author": {
        "name": "政经鲁社长",
        "handle": "xzzzjpl",
        "profileUrl": "https://x.com/xzzzjpl"
      },
      "text": "大老王如果竞选成功，是不是必须得退出拿性教教主？看来我有机会了。",
      "translated": false,
      "createdAt": "2026-07-04T02:41:45.000Z",
      "visibleTime": "13h",
      "metrics": {
        "replies": "120",
        "reposts": "3",
        "likes": "226",
        "bookmarks": "7",
        "views": "104081"
      },
      "images": [],
      "links": [],
      "relation": "visible-reply"
    },
    {
      "index": 4,
      "id": "2073258238519177660",
      "url": "https://x.com/giantcutie666/status/2073258238519177660",
      "author": {
        "name": "大漂亮| C Labs",
        "handle": "giantcutie666",
        "profileUrl": "https://x.com/giantcutie666"
      },
      "text": "中国人口自2022年开始进入负增长，各省开始抢人，这是中国人这四年来用脚投票的结果：\n\n东三省人口流失最严重，无可救药\n\n紧随其后的是山河四省\n\n不知道是不是因为不卷，新疆、西藏的人口都大幅度增长\n\n在人口大省中，只有广东在生娃，有自然增长\n\n而浙江、海南、江苏都在吸其他省市的流入人口",
      "translated": false,
      "createdAt": "2026-07-04T04:10:57.000Z",
      "visibleTime": "11h",
      "metrics": {
        "replies": "53",
        "reposts": "16",
        "likes": "119",
        "bookmarks": "31",
        "views": "26903"
      },
      "images": [
        {
          "alt": "Image",
          "url": "https://pbs.twimg.com/media/HMWxYYlWMAAkE2V?format=jpg&name=large"
        },
        {
          "alt": "Image",
          "url": "https://pbs.twimg.com/media/HMWxYaAXAAA9m8Y?format=jpg&name=large"
        }
      ],
      "links": [],
      "relation": "visible-reply"
    }
  ]
}
