{
  "index": 0,
  "id": "2072948156266914085",
  "url": "https://x.com/wufantouzi/status/2072948156266914085",
  "author": {
    "name": "wu fan",
    "handle": "wufantouzi",
    "profileUrl": "https://x.com/wufantouzi"
  },
  "text": "稳定币赛道里\n当之无愧的龙头肯定是usdt\n它野蛮生长\n没有合规身份\n从0干到2000亿美金\n\n如果有机会200亿美金市值\n买到合规的tether\n我肯定不会错过\n但没有如果\n\n所以面对crcl\n不能不动心\n对于胜率25%还是90%我需要重申\n可能很对人对此有误解\n\n如果按照常规算法\n只能按照市场占有率去计算它就是24%左右\n在10-25%区间波动（去年到今年）\n\n但是如果考虑合规稳定币\ncrcl的usdc占比就接近90%了\n如果你认为usdt迟早要被干掉被处罚或者限制\n那么crcl作为合规稳定币龙头胜率就是90%+\n\n我们不能考虑没有usdt的情形\n也就是说基于客观事实\n目前crcl的胜率大约在25%\n但是我自己的判断我下重注\n是因为我按照合规市场的占有率下注\n我个人认为他有90%+\n\n要区分客观事实\n和我的主观判断的区别",
  "translated": false,
  "createdAt": "2026-07-03T07:38:48.000Z",
  "visibleTime": "3:38 PM · Jul 3, 2026",
  "metrics": {
    "replies": "59",
    "reposts": "5",
    "likes": "94",
    "bookmarks": "11",
    "views": "26896"
  },
  "images": [],
  "links": [],
  "schemaVersion": 3,
  "source": "x",
  "capturedAt": "2026-07-04T15:32:09.768Z",
  "capturedFromUrl": "https://x.com/wufantouzi/status/2072948156266914085",
  "blockedCommentCount": 0,
  "comments": [
    {
      "index": 1,
      "id": "2073342803820880160",
      "url": "https://x.com/kakapawang1/status/2073342803820880160",
      "author": {
        "name": "kakapawang",
        "handle": "kakapawang1",
        "profileUrl": "https://x.com/kakapawang1"
      },
      "text": "没有合规身份的USDT不久就要被美国制裁了。",
      "translated": false,
      "createdAt": "2026-07-04T09:46:59.000Z",
      "visibleTime": "5h",
      "metrics": {
        "views": "42"
      },
      "images": [],
      "links": [],
      "relation": "visible-reply"
    },
    {
      "index": 0,
      "id": "2073048990862766372",
      "url": "https://x.com/m____229/status/2073048990862766372",
      "author": {
        "name": "拉波尔特",
        "handle": "m____229",
        "profileUrl": "https://x.com/m____229"
      },
      "text": "USDT野蛮生长是真的猛，但CRCL想逆袭可太难了吧。",
      "translated": false,
      "createdAt": "2026-07-03T14:19:29.000Z",
      "visibleTime": "Jul 3",
      "metrics": {
        "views": "698"
      },
      "images": [],
      "links": [],
      "relation": "visible-reply"
    },
    {
      "index": 1,
      "id": "2072973831535575278",
      "url": "https://x.com/ludan168/status/2072973831535575278",
      "author": {
        "name": "卤蛋",
        "handle": "ludan168",
        "profileUrl": "https://x.com/ludan168"
      },
      "text": "跌了来骂 涨了不吭声 这些人是真没出息  永远穷逼",
      "translated": false,
      "createdAt": "2026-07-03T09:20:50.000Z",
      "visibleTime": "Jul 3",
      "metrics": {
        "likes": "4",
        "views": "1287"
      },
      "images": [],
      "links": [],
      "relation": "visible-reply"
    },
    {
      "index": 2,
      "id": "2072951897431122023",
      "url": "https://x.com/dreamback2012/status/2072951897431122023",
      "author": {
        "name": "Rain",
        "handle": "dreamback2012",
        "profileUrl": "https://x.com/dreamback2012"
      },
      "text": "激烈交锋，过几年回头来看。\nQuote\nMindao\n@mindaoyang\nJul 1\nOpenUSD is the true Libra dollar version\n\nFor Circle, it's basically pulling the rug out from under them\n\nThe three factions of stablecoins in the crypto world are: the pro-establishment USDC, the decentralized USDS/DAI, and the wild USDT; and the weakest moat is USDC's x.com/fishkiller/sta…",
      "translated": false,
      "createdAt": "2026-07-03T07:53:40.000Z",
      "visibleTime": "Jul 3",
      "metrics": {
        "views": "2709"
      },
      "images": [],
      "links": [],
      "relation": "visible-reply"
    },
    {
      "index": 3,
      "id": "2072965220134535458",
      "url": "https://x.com/MrLaoFou/status/2072965220134535458",
      "author": {
        "name": "老否先生",
        "handle": "MrLaoFou",
        "profileUrl": "https://x.com/MrLaoFou"
      },
      "text": "crcl会胜的，ousd就是乌合之众\n只不过是想增加博弈的筹码",
      "translated": false,
      "createdAt": "2026-07-03T08:46:36.000Z",
      "visibleTime": "Jul 3",
      "metrics": {
        "likes": "4",
        "views": "1113"
      },
      "images": [],
      "links": [],
      "relation": "visible-reply"
    },
    {
      "index": 5,
      "id": "2072977647123272000",
      "url": "https://x.com/AndyLiu31174222/status/2072977647123272000",
      "author": {
        "name": "KFCV50",
        "handle": "AndyLiu31174222",
        "profileUrl": "https://x.com/AndyLiu31174222"
      },
      "text": "理他们干啥，一群乌合之众而已。",
      "translated": false,
      "createdAt": "2026-07-03T09:35:59.000Z",
      "visibleTime": "Jul 3",
      "metrics": {
        "like": "1",
        "views": "474"
      },
      "images": [],
      "links": [],
      "relation": "visible-reply"
    },
    {
      "index": 6,
      "id": "2072970805643038895",
      "url": "https://x.com/zhourf212080/status/2072970805643038895",
      "author": {
        "name": "Mr.L",
        "handle": "zhourf212080",
        "profileUrl": "https://x.com/zhourf212080"
      },
      "text": "不用管他们",
      "translated": false,
      "createdAt": "2026-07-03T09:08:48.000Z",
      "visibleTime": "Jul 3",
      "metrics": {
        "views": "545"
      },
      "images": [],
      "links": [],
      "relation": "visible-reply"
    },
    {
      "index": 7,
      "id": "2073041830799946203",
      "url": "https://x.com/thedratebi/status/2073041830799946203",
      "author": {
        "name": "Drake船长的笔记",
        "handle": "thedratebi",
        "profileUrl": "https://x.com/thedratebi"
      },
      "text": "CRCL最核心的分歧就在这里。\n如果USDT继续稳坐龙头，那USDC只是老二，估值自然要打折。\n但如果未来监管真把灰色美元需求往合规入口赶，USDC的地位就会被重新定价，问题是这个剧本什么时候发生、能不能发生。",
      "translated": false,
      "createdAt": "2026-07-03T13:51:02.000Z",
      "visibleTime": "Jul 3",
      "metrics": {
        "like": "1",
        "views": "355"
      },
      "images": [],
      "links": [],
      "relation": "visible-reply"
    },
    {
      "index": 0,
      "id": "2073032553699881397",
      "url": "https://x.com/hafiz_alan/status/2073032553699881397",
      "author": {
        "name": "wu fon.",
        "handle": "hafiz_alan",
        "profileUrl": "https://x.com/hafiz_alan"
      },
      "text": "我的投资策略",
      "translated": false,
      "createdAt": "2026-07-03T13:14:10.000Z",
      "visibleTime": "Jul 3",
      "metrics": {
        "reply": "1",
        "bookmark": "1",
        "views": "284"
      },
      "images": [],
      "links": [],
      "relation": "visible-reply"
    },
    {
      "index": 1,
      "id": "2073083834149831136",
      "url": "https://x.com/Tianhshow/status/2073083834149831136",
      "author": {
        "name": "Mr.t",
        "handle": "Tianhshow",
        "profileUrl": "https://x.com/Tianhshow"
      },
      "text": "大鳄已经联合起来杀入稳定币赛道了，如果他只在加密领域玩潜力有限，如果他去传统金融领域又玩不过传统的，这是竞争格局，不能过度乐观，目前看走一步往后看两步更好点",
      "translated": false,
      "createdAt": "2026-07-03T16:37:56.000Z",
      "visibleTime": "22h",
      "metrics": {
        "like": "1",
        "views": "228"
      },
      "images": [],
      "links": [],
      "relation": "visible-reply"
    },
    {
      "index": 2,
      "id": "2072963684130033961",
      "url": "https://x.com/hangtouhangnao/status/2072963684130033961",
      "author": {
        "name": "夯头夯脑",
        "handle": "hangtouhangnao",
        "profileUrl": "https://x.com/hangtouhangnao"
      },
      "text": "老师别洗了，usdc的护城河太低了",
      "translated": false,
      "createdAt": "2026-07-03T08:40:30.000Z",
      "visibleTime": "Jul 3",
      "metrics": {
        "views": "430"
      },
      "images": [],
      "links": [],
      "relation": "visible-reply"
    },
    {
      "index": 3,
      "id": "2072965215784984876",
      "url": "https://x.com/billsoon7/status/2072965215784984876",
      "author": {
        "name": "billsoon",
        "handle": "billsoon7",
        "profileUrl": "https://x.com/billsoon7"
      },
      "text": "",
      "translated": false,
      "createdAt": "2026-07-03T08:46:35.000Z",
      "visibleTime": "Jul 3",
      "metrics": {
        "views": "341"
      },
      "images": [],
      "links": [],
      "relation": "visible-reply"
    },
    {
      "index": 0,
      "id": "2072950322356711466",
      "url": "https://x.com/zhuxiaohe2021/status/2072950322356711466",
      "author": {
        "name": "索卫兵(Solana)",
        "handle": "zhuxiaohe2021",
        "profileUrl": "https://x.com/zhuxiaohe2021"
      },
      "text": "挂单中，希望能跌破60以下，甚至50以下",
      "translated": false,
      "createdAt": "2026-07-03T07:47:25.000Z",
      "visibleTime": "Jul 3",
      "metrics": {
        "views": "750"
      },
      "images": [],
      "links": [],
      "relation": "visible-reply"
    },
    {
      "index": 2,
      "id": "2072955393702326366",
      "url": "https://x.com/YxSebastian/status/2072955393702326366",
      "author": {
        "name": "Sebastian",
        "handle": "YxSebastian",
        "profileUrl": "https://x.com/YxSebastian"
      },
      "text": "USDT有风险。",
      "translated": false,
      "createdAt": "2026-07-03T08:07:34.000Z",
      "visibleTime": "Jul 3",
      "metrics": {
        "like": "1",
        "views": "426"
      },
      "images": [],
      "links": [],
      "relation": "visible-reply"
    },
    {
      "index": 3,
      "id": "2072956809019842740",
      "url": "https://x.com/nbyfhx/status/2072956809019842740",
      "author": {
        "name": "nb666.eth",
        "handle": "nbyfhx",
        "profileUrl": "https://x.com/nbyfhx"
      },
      "text": "傻逼",
      "translated": false,
      "createdAt": "2026-07-03T08:13:11.000Z",
      "visibleTime": "Jul 3",
      "metrics": {
        "reply": "1",
        "views": "493"
      },
      "images": [],
      "links": [],
      "relation": "visible-reply"
    },
    {
      "index": 4,
      "id": "2072952763181597063",
      "url": "https://x.com/msx168/status/2072952763181597063",
      "author": {
        "name": "麦通MSX｜代理招募",
        "handle": "msx168",
        "profileUrl": "https://x.com/msx168"
      },
      "text": "老师分析没问题，\n\n稳定币万亿市场，容得下大家！",
      "translated": false,
      "createdAt": "2026-07-03T07:57:06.000Z",
      "visibleTime": "Jul 3",
      "metrics": {
        "likes": "2",
        "views": "647"
      },
      "images": [],
      "links": [],
      "relation": "visible-reply"
    },
    {
      "index": 5,
      "id": "2073013411559121144",
      "url": "https://x.com/BNZCDY/status/2073013411559121144",
      "author": {
        "name": "币安交易所高返佣注册",
        "handle": "BNZCDY",
        "profileUrl": "https://x.com/BNZCDY"
      },
      "text": "Fan account\n没有合规身份",
      "translated": false,
      "createdAt": "2026-07-03T11:58:06.000Z",
      "visibleTime": "Jul 3",
      "metrics": {
        "views": "119"
      },
      "images": [],
      "links": [
        {
          "text": "Fan account",
          "url": "https://help.x.com/rules-and-policies/authenticity"
        }
      ],
      "relation": "visible-reply"
    },
    {
      "index": 6,
      "id": "2072952190894063927",
      "url": "https://x.com/CryptoFenggebtc/status/2072952190894063927",
      "author": {
        "name": "比特币峰哥",
        "handle": "CryptoFenggebtc",
        "profileUrl": "https://x.com/CryptoFenggebtc"
      },
      "text": "赌一把合规后crcl受益最大",
      "translated": false,
      "createdAt": "2026-07-03T07:54:50.000Z",
      "visibleTime": "Jul 3",
      "metrics": {
        "views": "578"
      },
      "images": [],
      "links": [],
      "relation": "visible-reply"
    },
    {
      "index": 7,
      "id": "2072967960990449873",
      "url": "https://x.com/sidelined_cap/status/2072967960990449873",
      "author": {
        "name": "踏空 Sidelined Capital",
        "handle": "sidelined_cap",
        "profileUrl": "https://x.com/sidelined_cap"
      },
      "text": "Quote\nJul 1\nMany people are bearish on Circle because of OUSD, but that's actually flawed logic. OUSD is a consortium and can't possibly go public. Tether won't go public either. Circle, as the only pure-play stablecoin concept among listed companies, is the biggest reason to invest in it.",
      "translated": true,
      "createdAt": "2026-07-03T08:57:30.000Z",
      "visibleTime": "Jul 3",
      "metrics": {
        "views": "467"
      },
      "images": [],
      "links": [],
      "relation": "visible-reply"
    },
    {
      "index": 8,
      "id": "2072951377685524604",
      "url": "https://x.com/PapinderB/status/2072951377685524604",
      "author": {
        "name": "悦悦(100+顶级博主VIP策略聚合群)",
        "handle": "PapinderB",
        "profileUrl": "https://x.com/PapinderB"
      },
      "text": "稳定币赛道分化会越来越明显，散户、海外交易所依赖 USDT，机构、美股 ETF、合规渠道只会认 USDC，两条资金线正在慢慢割裂。",
      "translated": false,
      "createdAt": "2026-07-03T07:51:36.000Z",
      "visibleTime": "Jul 3",
      "metrics": {
        "bookmark": "1",
        "views": "770"
      },
      "images": [],
      "links": [],
      "relation": "visible-reply"
    },
    {
      "index": 9,
      "id": "2072980877211275496",
      "url": "https://x.com/quschdnjs/status/2072980877211275496",
      "author": {
        "name": "Michael 宝塔镇河妖",
        "handle": "quschdnjs",
        "profileUrl": "https://x.com/quschdnjs"
      },
      "text": "哥们，我赌90%那一边",
      "translated": false,
      "createdAt": "2026-07-03T09:48:49.000Z",
      "visibleTime": "Jul 3",
      "metrics": {
        "views": "162"
      },
      "images": [],
      "links": [],
      "relation": "visible-reply"
    },
    {
      "index": 10,
      "id": "2072949243594318182",
      "url": "https://x.com/ablenavy/status/2072949243594318182",
      "author": {
        "name": "iGarlic",
        "handle": "ablenavy",
        "profileUrl": "https://x.com/ablenavy"
      },
      "text": "USDT是野蛮生长的“坏孩子”，CRCL则是乖巧的“三好学生”。下注的话，我选不被抓的那个！",
      "translated": false,
      "createdAt": "2026-07-03T07:43:07.000Z",
      "visibleTime": "Jul 3",
      "metrics": {
        "views": "563"
      },
      "images": [],
      "links": [],
      "relation": "visible-reply"
    },
    {
      "index": 11,
      "id": "2073066329784131893",
      "url": "https://x.com/_TAOLIMAO/status/2073066329784131893",
      "author": {
        "name": "0xMao",
        "handle": "_TAOLIMAO",
        "profileUrl": "https://x.com/_TAOLIMAO"
      },
      "text": "涨起来大儒又要辩经了",
      "translated": false,
      "createdAt": "2026-07-03T15:28:23.000Z",
      "visibleTime": "Jul 3",
      "metrics": {
        "likes": "2",
        "views": "592"
      },
      "images": [],
      "links": [],
      "relation": "visible-reply"
    },
    {
      "index": 12,
      "id": "2072973107694829905",
      "url": "https://x.com/sogimester/status/2072973107694829905",
      "author": {
        "name": "sogi.hl",
        "handle": "sogimester",
        "profileUrl": "https://x.com/sogimester"
      },
      "text": "25% or 90% both feel like roulette picks for a stablecoin bet\n\nid take the 90% side just for the thesis gamble",
      "translated": false,
      "createdAt": "2026-07-03T09:17:57.000Z",
      "visibleTime": "Jul 3",
      "metrics": {
        "views": "275"
      },
      "images": [],
      "links": [],
      "relation": "visible-reply"
    }
  ]
}
